{
    "carousel": [
        {
            "articleId": "pronoia-waanidee-alles-in-je-voordeel",
            "category": "faitsdivers"
        },
        {
            "articleId": "gevangene-vond-tandenborstel-uit",
            "category": "mensen"
        },
        {
            "articleId": "mr-bean-bestuurt-vliegtuig",
            "category": "entertainment"
        }
    ],
    "articles": [
        {
            "articleId": "je-ziet-sneller-slang-dan-spin",
            "category": "wetenschap"
        },
        {
            "articleId": "voetbal-zwart-wit-voor-tv-kijkers",
            "category": "geschiedenis"
        },
        {
            "articleId": "michael-phelps-olympisch-record",
            "category": "mensen"
        },
        {
            "articleId": "vos-heeft-snorharen-aan-poten",
            "category": "natuur"
        },
        {
            "articleId": "halle-berry-stunt-double-man",
            "category": "entertainment"
        },
        {
            "articleId": "word-lid-orde-van-de-feniks",
            "category": "faitsdivers"
        }
    ]
}